src/__init__.py
src/entry.py
src/log_utility.py
src/pack_log.py
src/public.py
src/v_t_chart.py
test/__init__.py
test/test_log_download.py
test/test_log_file_name_match.py
test/test_log_utility.py
test/test_read_pick_data.py
test/test_read_sort_data.py
test/test_tiem_range.py
hc_log_filter-1.2.7.dist-info/LICENSE
hc_log_filter-1.2.7.dist-info/METADATA
hc_log_filter-1.2.7.dist-info/WHEEL
hc_log_filter-1.2.7.dist-info/top_level.txt
hc_log_filter-1.2.7.dist-info/RECORD
